[
    {
        "id": 857,
        "image": "AMBER_857.jpg",
        "query": "Describe this image."
    },
    {
        "id": 401,
        "image": "AMBER_401.jpg",
        "query": "Describe this image."
    },
    {
        "id": 264,
        "image": "AMBER_264.jpg",
        "query": "Describe this image."
    },
    {
        "id": 681,
        "image": "AMBER_681.jpg",
        "query": "Describe this image."
    },
    {
        "id": 26,
        "image": "AMBER_26.jpg",
        "query": "Describe this image."
    },
    {
        "id": 793,
        "image": "AMBER_793.jpg",
        "query": "Describe this image."
    },
    {
        "id": 710,
        "image": "AMBER_710.jpg",
        "query": "Describe this image."
    },
    {
        "id": 203,
        "image": "AMBER_203.jpg",
        "query": "Describe this image."
    },
    {
        "id": 107,
        "image": "AMBER_107.jpg",
        "query": "Describe this image."
    },
    {
        "id": 872,
        "image": "AMBER_872.jpg",
        "query": "Describe this image."
    },
    {
        "id": 270,
        "image": "AMBER_270.jpg",
        "query": "Describe this image."
    },
    {
        "id": 643,
        "image": "AMBER_643.jpg",
        "query": "Describe this image."
    },
    {
        "id": 372,
        "image": "AMBER_372.jpg",
        "query": "Describe this image."
    },
    {
        "id": 159,
        "image": "AMBER_159.jpg",
        "query": "Describe this image."
    },
    {
        "id": 552,
        "image": "AMBER_552.jpg",
        "query": "Describe this image."
    },
    {
        "id": 19,
        "image": "AMBER_19.jpg",
        "query": "Describe this image."
    },
    {
        "id": 70,
        "image": "AMBER_70.jpg",
        "query": "Describe this image."
    },
    {
        "id": 497,
        "image": "AMBER_497.jpg",
        "query": "Describe this image."
    },
    {
        "id": 678,
        "image": "AMBER_678.jpg",
        "query": "Describe this image."
    },
    {
        "id": 622,
        "image": "AMBER_622.jpg",
        "query": "Describe this image."
    },
    {
        "id": 23,
        "image": "AMBER_23.jpg",
        "query": "Describe this image."
    },
    {
        "id": 880,
        "image": "AMBER_880.jpg",
        "query": "Describe this image."
    },
    {
        "id": 241,
        "image": "AMBER_241.jpg",
        "query": "Describe this image."
    },
    {
        "id": 699,
        "image": "AMBER_699.jpg",
        "query": "Describe this image."
    },
    {
        "id": 858,
        "image": "AMBER_858.jpg",
        "query": "Describe this image."
    },
    {
        "id": 842,
        "image": "AMBER_842.jpg",
        "query": "Describe this image."
    },
    {
        "id": 698,
        "image": "AMBER_698.jpg",
        "query": "Describe this image."
    },
    {
        "id": 903,
        "image": "AMBER_903.jpg",
        "query": "Describe this image."
    },
    {
        "id": 997,
        "image": "AMBER_997.jpg",
        "query": "Describe this image."
    },
    {
        "id": 684,
        "image": "AMBER_684.jpg",
        "query": "Describe this image."
    },
    {
        "id": 827,
        "image": "AMBER_827.jpg",
        "query": "Describe this image."
    },
    {
        "id": 962,
        "image": "AMBER_962.jpg",
        "query": "Describe this image."
    },
    {
        "id": 164,
        "image": "AMBER_164.jpg",
        "query": "Describe this image."
    },
    {
        "id": 220,
        "image": "AMBER_220.jpg",
        "query": "Describe this image."
    },
    {
        "id": 347,
        "image": "AMBER_347.jpg",
        "query": "Describe this image."
    },
    {
        "id": 595,
        "image": "AMBER_595.jpg",
        "query": "Describe this image."
    },
    {
        "id": 802,
        "image": "AMBER_802.jpg",
        "query": "Describe this image."
    },
    {
        "id": 461,
        "image": "AMBER_461.jpg",
        "query": "Describe this image."
    },
    {
        "id": 957,
        "image": "AMBER_957.jpg",
        "query": "Describe this image."
    },
    {
        "id": 353,
        "image": "AMBER_353.jpg",
        "query": "Describe this image."
    },
    {
        "id": 998,
        "image": "AMBER_998.jpg",
        "query": "Describe this image."
    },
    {
        "id": 176,
        "image": "AMBER_176.jpg",
        "query": "Describe this image."
    },
    {
        "id": 121,
        "image": "AMBER_121.jpg",
        "query": "Describe this image."
    },
    {
        "id": 528,
        "image": "AMBER_528.jpg",
        "query": "Describe this image."
    },
    {
        "id": 48,
        "image": "AMBER_48.jpg",
        "query": "Describe this image."
    },
    {
        "id": 465,
        "image": "AMBER_465.jpg",
        "query": "Describe this image."
    },
    {
        "id": 909,
        "image": "AMBER_909.jpg",
        "query": "Describe this image."
    },
    {
        "id": 137,
        "image": "AMBER_137.jpg",
        "query": "Describe this image."
    },
    {
        "id": 996,
        "image": "AMBER_996.jpg",
        "query": "Describe this image."
    },
    {
        "id": 443,
        "image": "AMBER_443.jpg",
        "query": "Describe this image."
    }
]